portlets/__init__.py
portlets/models.py
portlets/templatetags/__init__.py
portlets/templatetags/portlet_tags.py
portlets-0.0.1.dist-info/LICENSE
portlets-0.0.1.dist-info/METADATA
portlets-0.0.1.dist-info/WHEEL
portlets-0.0.1.dist-info/top_level.txt
portlets-0.0.1.dist-info/RECORD
