Metadata-Version: 2.1
Name: portlets
Version: 0.0.1
Summary: Portlets
Home-page: https://gitlab.com/pytekbg/portlets
Author: mladen
Author-email: mladengeorgiev18@abv.bg
License: UNKNOWN
Project-URL: Bug Tracker, https://gitlab.com/pytekbg/portlets/issues
Platform: UNKNOWN
Classifier: Programming Language :: Python :: 3
Classifier: License :: OSI Approved :: MIT License
Classifier: Operating System :: OS Independent
Requires-Python: >=3.6
License-File: LICENSE
